{
  "eventId": "2718",
  "documentCode": "TTEMSINGLES--------U15GP01000200----------",
  "subEventName": "U15 Boys' Singles",
  "subEventDescription": "U15 Boys' Singles - Group 1 - Match 2",
  "matchConfig": {
    "bestOfXGames": 5,
    "maxPointsPerGame": 11,
    "advantagePerGame": 2,
    "suddenDeathPoint": 99,
    "maxChallengesPerCompetitor": 2,
    "yellowCard": true,
    "yellowRed1": true,
    "yellowRed2": true,
    "tTRReview": true
  },
  "venueName": "Townsville Stadium",
  "tableNumber": "T03",
  "tableName": "Table 3",
  "competitiors": [
    {
      "competitorType": "H",
      "competitiorId": "200231",
      "competitiorName": "HO Eli",
      "competitiorOrg": "NZL",
      "compCardY": "0",
      "compCardYR1": "0",
      "compCardYR2": "0",
      "compTimeout": "0",
      "compMedicalTimeout": "",
      "players": [
        {
          "playerId": "200231",
          "playerName": "HO Eli",
          "playerGivenName": null,
          "playerFamilyName": null,
          "playerOrgCode": "NZL",
          "playerPosition": 1
        }
      ],
      "scores": "11,11,12,0,0",
      "irm": null
    },
    {
      "competitorType": "A",
      "competitiorId": "202915",
      "competitiorName": "ZHOU Cheng",
      "competitiorOrg": "FIJ",
      "compCardY": "0",
      "compCardYR1": "0",
      "compCardYR2": "0",
      "compTimeout": "0",
      "compMedicalTimeout": "",
      "players": [
        {
          "playerId": "202915",
          "playerName": "ZHOU Cheng",
          "playerGivenName": null,
          "playerFamilyName": null,
          "playerOrgCode": "FIJ",
          "playerPosition": 2
        }
      ],
      "scores": "4,4,10,0,0",
      "irm": null
    }
  ],
  "currentGameNumber": 3,
  "full_msg": null,
  "gameScores": "11-4,11-4,12-10,0-0,0-0",
  "resultsGameScores": "11-4,11-4,12-10,0-0,0-0",
  "overallScores": "3-0",
  "resultOverallScores": "3-0",
  "resultStatus": "OFFICIAL",
  "action": {
    "actionType": "OF",
    "serverPlayer": "202915",
    "serverReceiver": "200231",
    "serverNext": "202915",
    "serverCompetitor": "202915",
    "receiverNext": "202915"
  },
  "resultSet": null,
  "matchDateTime": {
    "duration": "00:00:00",
    "startDateLocal": "09/06/2023 09:20:00",
    "startDateUTC": "09/05/2023 23:20:00"
  },
  "teamParentData": null,
  "playByPlaySequenceNumber": "2"
}