{
  "eventId": "2879",
  "documentCode": "TTEWDOUBLES-----------8FNL000700----------",
  "subEventName": "Women's Doubles",
  "subEventDescription": "Women's Doubles - Round of 16 - Match 7",
  "matchConfig": {
    "bestOfXGames": 5,
    "maxPointsPerGame": 11,
    "advantagePerGame": 2,
    "suddenDeathPoint": 99,
    "maxChallengesPerCompetitor": 99,
    "yellowCard": true,
    "yellowRed1": true,
    "yellowRed2": true,
    "tTRReview": false
  },
  "venueName": "National Cycling Centre",
  "tableNumber": "T03",
  "tableName": "Table 3",
  "competitiors": [
    {
      "competitorType": "H",
      "competitiorId": "100119029",
      "competitiorName": "ZARIF Audrey/COK Isa",
      "competitiorOrg": "FRA",
      "compCardY": "0",
      "compCardYR1": "0",
      "compCardYR2": "0",
      "compTimeout": "0",
      "compMedicalTimeout": "",
      "players": [
        {
          "playerId": "116874",
          "playerName": "ZARIF Audrey",
          "playerGivenName": null,
          "playerFamilyName": null,
          "playerOrgCode": "FRA",
          "playerPosition": 1
        },
        {
          "playerId": "131846",
          "playerName": "COK Isa",
          "playerGivenName": null,
          "playerFamilyName": null,
          "playerOrgCode": "FRA",
          "playerPosition": 2
        }
      ],
      "scores": "10,11,11,7,7",
      "irm": null
    },
    {
      "competitorType": "A",
      "competitiorId": "100118997",
      "competitiorName": "EARLEY Sophie/YU Tianer",
      "competitiorOrg": "ENG",
      "compCardY": "0",
      "compCardYR1": "0",
      "compCardYR2": "0",
      "compTimeout": "1",
      "compMedicalTimeout": "",
      "players": [
        {
          "playerId": "134575",
          "playerName": "EARLEY Sophie",
          "playerGivenName": null,
          "playerFamilyName": null,
          "playerOrgCode": "ENG",
          "playerPosition": 1
        },
        {
          "playerId": "203536",
          "playerName": "YU Tianer",
          "playerGivenName": null,
          "playerFamilyName": null,
          "playerOrgCode": "ENG",
          "playerPosition": 2
        }
      ],
      "scores": "12,5,7,11,11",
      "irm": null
    }
  ],
  "currentGameNumber": 5,
  "full_msg": null,
  "gameScores": "10-12,11-5,11-7,7-11,7-11",
  "resultsGameScores": "10-12,11-5,11-7,7-11,7-11",
  "overallScores": "2-3",
  "resultOverallScores": "2-3",
  "resultStatus": "OFFICIAL",
  "action": {
    "actionType": "OF",
    "serverPlayer": "134575",
    "serverReceiver": "131846",
    "serverNext": "134575",
    "serverCompetitor": "100118997",
    "receiverNext": "131846"
  },
  "resultSet": null,
  "matchDateTime": {
    "duration": "00:32:24",
    "startDateLocal": "02/02/2024 14:05:00",
    "startDateUTC": "02/02/2024 14:05:00"
  },
  "teamParentData": null,
  "playByPlaySequenceNumber": "262",
  "teamMatchNo": "0",
  "teamMatchScores": "0-0,0-0,0-0,0-0,0-0",
  "teamMatchScoresSummary": "0"
}