{
  "eventId": "2694",
  "documentCode": "TTEWDOUBLES-----------8FNL000500----------",
  "subEventName": "Women's Doubles",
  "subEventDescription": "Women's Doubles - Round of 16 - Match 5",
  "matchConfig": {
    "bestOfXGames": 5,
    "maxPointsPerGame": 11,
    "advantagePerGame": 2,
    "suddenDeathPoint": 99,
    "maxChallengesPerCompetitor": 99,
    "yellowCard": true,
    "yellowRed1": true,
    "yellowRed2": true,
    "tTRReview": false
  },
  "venueName": "Hala Tivoli",
  "tableNumber": "T02",
  "tableName": "Table 2",
  "competitiors": [
    {
      "competitorType": "H",
      "competitiorId": "37521",
      "competitiorName": "LUTZ Camille/PAVADE Prithika",
      "competitiorOrg": "FRA",
      "compCardY": "0",
      "compCardYR1": "0",
      "compCardYR2": "0",
      "compTimeout": "0",
      "compMedicalTimeout": "",
      "players": [
        {
          "playerId": "123550",
          "playerName": "LUTZ Camille",
          "playerGivenName": null,
          "playerFamilyName": null,
          "playerOrgCode": null,
          "playerPosition": 1
        },
        {
          "playerId": "131100",
          "playerName": "PAVADE Prithika",
          "playerGivenName": null,
          "playerFamilyName": null,
          "playerOrgCode": null,
          "playerPosition": 2
        }
      ],
      "scores": "13,11,11,0,0",
      "irm": null
    },
    {
      "competitorType": "A",
      "competitiorId": "55792",
      "competitiorName": "TOFANT Ana/TOKIC Sara",
      "competitiorOrg": "SLO",
      "compCardY": "0",
      "compCardYR1": "0",
      "compCardYR2": "0",
      "compTimeout": "1",
      "compMedicalTimeout": "",
      "players": [
        {
          "playerId": "122842",
          "playerName": "TOFANT Ana",
          "playerGivenName": null,
          "playerFamilyName": null,
          "playerOrgCode": null,
          "playerPosition": 1
        },
        {
          "playerId": "133426",
          "playerName": "TOKIC Sara",
          "playerGivenName": null,
          "playerFamilyName": null,
          "playerOrgCode": null,
          "playerPosition": 2
        }
      ],
      "scores": "11,7,6,0,0",
      "irm": null
    }
  ],
  "currentGameNumber": 3,
  "full_msg": null,
  "gameScores": "13-11,11-7,11-6,0-0,0-0",
  "resultsGameScores": "13-11,11-7,11-6,0-0,0-0",
  "overallScores": "3-0",
  "resultOverallScores": "3-0",
  "resultStatus": "OFFICIAL",
  "action": {
    "actionType": "OF",
    "serverPlayer": "133426",
    "serverReceiver": "123550",
    "serverNext": "133426",
    "serverCompetitor": "55792",
    "receiverNext": "123550"
  },
  "resultSet": null,
  "matchDateTime": {
    "duration": "00:20:55",
    "startDateLocal": "07/05/2023 14:45:00",
    "startDateUTC": "07/05/2023 12:45:00"
  },
  "teamParentData": null,
  "playByPlaySequenceNumber": "162"
}