{
  "eventId": "2410",
  "documentCode": "TTEMSINGLES-----------RND1005100--",
  "subEventName": "Men Singles",
  "subEventDescription": "Men's Singles - Preliminary Round 1 - Match 51",
  "matchConfig": {
    "bestOfXGames": 5,
    "maxPointsPerGame": 11,
    "advantagePerGame": 2,
    "suddenDeathPoint": 99,
    "maxChallengesPerCompetitor": 2,
    "yellowCard": true,
    "yellowRed1": true,
    "yellowRed2": true,
    "tTRReview": null
  },
  "venueName": "Lusail Sports Arena",
  "tableNumber": "T02",
  "tableName": "Table 2",
  "competitiors": [
    {
      "competitorType": "H",
      "competitiorId": "112361",
      "competitiorName": "TAUBER Michael",
      "competitiorOrg": "ISR",
      "compCardY": "0",
      "compCardYR1": "0",
      "compCardYR2": "0",
      "compTimeout": "1",
      "compMedicalTimeout": "",
      "players": [
        {
          "playerId": "112361",
          "playerName": "TAUBER Michael",
          "playerGivenName": null,
          "playerFamilyName": null,
          "playerOrgCode": "ISR",
          "playerPosition": 1
        }
      ],
      "scores": "9,8,11,0,0"
    },
    {
      "competitorType": "A",
      "competitiorId": "110602",
      "competitiorName": "ZHMUDENKO Yaroslav",
      "competitiorOrg": "UKR",
      "compCardY": "0",
      "compCardYR1": "0",
      "compCardYR2": "0",
      "compTimeout": "0",
      "compMedicalTimeout": "",
      "players": [
        {
          "playerId": "110602",
          "playerName": "ZHMUDENKO Yaroslav",
          "playerGivenName": null,
          "playerFamilyName": null,
          "playerOrgCode": "UKR",
          "playerPosition": 2
        }
      ],
      "scores": "11,11,13,0,0"
    }
  ],
  "currentGameNumber": 3,
  "full_msg": null,
  "gameScores": "9-11,8-11,11-13,0-0,0-0",
  "resultsGameScores": "9-11,8-11,11-13",
  "overallScores": "0-3",
  "resultOverallScores": "0-3",
  "resultStatus": "OFFICIAL",
  "action": {
    "actionType": "PT",
    "serverPlayer": "110602",
    "serverReceiver": "112361",
    "serverNext": null,
    "serverCompetitor": "110602",
    "receiverNext": null
  },
  "resultSet": null,
  "matchDateTime": {
    "duration": "00:25:46",
    "startDateLocal": "02/28/2021 09:00:00",
    "startDateUTC": "02/28/2021 09:00:00"
  },
  "teamParentData": null
}