{
  "eventId": "2701",
  "documentCode": "TTEXDOUBLES-----------SFNL000200----------",
  "subEventName": "Mixed Doubles",
  "subEventDescription": "Mixed Doubles - Semifinal - Match 2",
  "matchConfig": {
    "bestOfXGames": 5,
    "maxPointsPerGame": 11,
    "advantagePerGame": 2,
    "suddenDeathPoint": 99,
    "maxChallengesPerCompetitor": 99,
    "yellowCard": true,
    "yellowRed1": true,
    "yellowRed2": true,
    "tTRReview": false
  },
  "venueName": "Lusail Sports Arena",
  "tableNumber": "T01",
  "tableName": "Table 1",
  "competitiors": [
    {
      "competitorType": "H",
      "competitiorId": "55556",
      "competitiorName": "XIANG Peng/QIAN Tianyi",
      "competitiorOrg": "CHN",
      "compCardY": "0",
      "compCardYR1": "0",
      "compCardYR2": "0",
      "compTimeout": "0",
      "compMedicalTimeout": "",
      "players": [
        {
          "playerId": "135888",
          "playerName": "XIANG Peng",
          "playerGivenName": null,
          "playerFamilyName": null,
          "playerOrgCode": null,
          "playerPosition": 1
        },
        {
          "playerId": "119797",
          "playerName": "QIAN Tianyi",
          "playerGivenName": null,
          "playerFamilyName": null,
          "playerOrgCode": null,
          "playerPosition": 2
        }
      ],
      "scores": "11,11,11,0,0",
      "irm": null
    },
    {
      "competitorType": "A",
      "competitiorId": "57490",
      "competitiorName": "REDZIMSKI Milosz/WEGRZYN Anna",
      "competitiorOrg": "POL",
      "compCardY": "0",
      "compCardYR1": "0",
      "compCardYR2": "0",
      "compTimeout": "0",
      "compMedicalTimeout": "",
      "players": [
        {
          "playerId": "135019",
          "playerName": "REDZIMSKI Milosz",
          "playerGivenName": null,
          "playerFamilyName": null,
          "playerOrgCode": null,
          "playerPosition": 1
        },
        {
          "playerId": "121040",
          "playerName": "WEGRZYN Anna",
          "playerGivenName": null,
          "playerFamilyName": null,
          "playerOrgCode": null,
          "playerPosition": 2
        }
      ],
      "scores": "1,7,5,0,0",
      "irm": null
    }
  ],
  "currentGameNumber": 3,
  "full_msg": null,
  "gameScores": "11-1,11-7,11-5,0-0,0-0",
  "resultsGameScores": "11-1,11-7,11-5,0-0,0-0",
  "overallScores": "3-0",
  "resultOverallScores": "3-0",
  "resultStatus": "OFFICIAL",
  "action": {
    "actionType": "OF",
    "serverPlayer": "119797",
    "serverReceiver": "121040",
    "serverNext": "119797",
    "serverCompetitor": "55556",
    "receiverNext": "121040"
  },
  "resultSet": null,
  "matchDateTime": {
    "duration": "00:35:14",
    "startDateLocal": "01/25/2023 14:05:00",
    "startDateUTC": "01/25/2023 11:05:00"
  },
  "teamParentData": null,
  "playByPlaySequenceNumber": "139"
}