{
  "eventId": "2696",
  "documentCode": "TTEWDOUBLES-----------8FNL000400----------",
  "subEventName": "Women's Doubles",
  "subEventDescription": "Women's Doubles - Round of 16 - Match 4",
  "matchConfig": {
    "bestOfXGames": 5,
    "maxPointsPerGame": 11,
    "advantagePerGame": 2,
    "suddenDeathPoint": 99,
    "maxChallengesPerCompetitor": 99,
    "yellowCard": true,
    "yellowRed1": true,
    "yellowRed2": true,
    "tTRReview": false
  },
  "venueName": "Dr. Shyama Prasad Mukherjee Indoor Stadium",
  "tableNumber": "T01",
  "tableName": "Table 1",
  "competitiors": [
    {
      "competitorType": "H",
      "competitiorId": "71330",
      "competitiorName": "BAJOR Natalia/HELMY Yousra",
      "competitiorOrg": "POL/EGY",
      "compCardY": "0",
      "compCardYR1": "0",
      "compCardYR2": "0",
      "compTimeout": "0",
      "compMedicalTimeout": "",
      "players": [
        {
          "playerId": "115454",
          "playerName": "BAJOR Natalia",
          "playerGivenName": null,
          "playerFamilyName": null,
          "playerOrgCode": "POL",
          "playerPosition": 1
        },
        {
          "playerId": "113908",
          "playerName": "HELMY Yousra",
          "playerGivenName": null,
          "playerFamilyName": null,
          "playerOrgCode": "EGY",
          "playerPosition": 2
        }
      ],
      "scores": "9,6,5,0,0",
      "irm": null
    },
    {
      "competitorType": "A",
      "competitiorId": "40379",
      "competitiorName": "MUKHERJEE Ayhika/MUKHERJEE Sutirtha",
      "competitiorOrg": "IND",
      "compCardY": "0",
      "compCardYR1": "0",
      "compCardYR2": "0",
      "compTimeout": "0",
      "compMedicalTimeout": "",
      "players": [
        {
          "playerId": "119537",
          "playerName": "MUKHERJEE Ayhika",
          "playerGivenName": null,
          "playerFamilyName": null,
          "playerOrgCode": "IND",
          "playerPosition": 1
        },
        {
          "playerId": "117365",
          "playerName": "MUKHERJEE Sutirtha",
          "playerGivenName": null,
          "playerFamilyName": null,
          "playerOrgCode": "IND",
          "playerPosition": 2
        }
      ],
      "scores": "11,11,11,0,0",
      "irm": null
    }
  ],
  "currentGameNumber": 3,
  "full_msg": null,
  "gameScores": "9-11,6-11,5-11,0-0,0-0",
  "resultsGameScores": "9-11,6-11,5-11,0-0,0-0",
  "overallScores": "0-3",
  "resultOverallScores": "0-3",
  "resultStatus": "OFFICIAL",
  "action": {
    "actionType": "OF",
    "serverPlayer": "115454",
    "serverReceiver": "119537",
    "serverNext": "115454",
    "serverCompetitor": "71330",
    "receiverNext": "119537"
  },
  "resultSet": null,
  "matchDateTime": {
    "duration": "00:10:55",
    "startDateLocal": "03/01/2023 11:10:00",
    "startDateUTC": "03/01/2023 05:40:00"
  },
  "teamParentData": null,
  "playByPlaySequenceNumber": "140",
  "teamMatchNo": "0",
  "teamMatchScores": "0-0,0-0,0-0,0-0,0-0",
  "teamMatchScoresSummary": "0"
}