{
  "eventId": "2932",
  "documentCode": "TTEWDOUBLES-----------8FNL000700----------",
  "subEventName": "Women's Doubles",
  "subEventDescription": "Women's Doubles - Round of 16 - Match 7",
  "matchConfig": {
    "bestOfXGames": 5,
    "maxPointsPerGame": 11,
    "advantagePerGame": 2,
    "suddenDeathPoint": 99,
    "maxChallengesPerCompetitor": 2,
    "yellowCard": true,
    "yellowRed1": true,
    "yellowRed2": true,
    "tTRReview": false
  },
  "venueName": "Sports Hall King Abdullah Sports City",
  "tableNumber": "T02",
  "tableName": "Table 2",
  "competitiors": [
    {
      "competitorType": "H",
      "competitiorId": "100119267",
      "competitiorName": "NAGASAKI Miyu/KIM Nayeong",
      "competitiorOrg": "JPN/KOR",
      "compCardY": "0",
      "compCardYR1": "0",
      "compCardYR2": "0",
      "compTimeout": "1",
      "compMedicalTimeout": "",
      "players": [
        {
          "playerId": "124591",
          "playerName": "NAGASAKI Miyu",
          "playerGivenName": null,
          "playerFamilyName": null,
          "playerOrgCode": "JPN",
          "playerPosition": 1
        },
        {
          "playerId": "133814",
          "playerName": "KIM Nayeong",
          "playerGivenName": null,
          "playerFamilyName": null,
          "playerOrgCode": "KOR",
          "playerPosition": 2
        }
      ],
      "scores": "6,11,10,11,11",
      "irm": null
    },
    {
      "competitorType": "A",
      "competitiorId": "40379",
      "competitiorName": "MUKHERJEE Ayhika/MUKHERJEE Sutirtha",
      "competitiorOrg": "IND",
      "compCardY": "0",
      "compCardYR1": "0",
      "compCardYR2": "0",
      "compTimeout": "1",
      "compMedicalTimeout": "",
      "players": [
        {
          "playerId": "119537",
          "playerName": "MUKHERJEE Ayhika",
          "playerGivenName": null,
          "playerFamilyName": null,
          "playerOrgCode": "IND",
          "playerPosition": 1
        },
        {
          "playerId": "117365",
          "playerName": "MUKHERJEE Sutirtha",
          "playerGivenName": null,
          "playerFamilyName": null,
          "playerOrgCode": "IND",
          "playerPosition": 2
        }
      ],
      "scores": "11,9,12,6,8",
      "irm": null
    }
  ],
  "currentGameNumber": 5,
  "full_msg": null,
  "gameScores": "6-11,11-9,10-12,11-6,11-8",
  "resultsGameScores": "6-11,11-9,10-12,11-6,11-8",
  "overallScores": "3-2",
  "resultOverallScores": "3-2",
  "resultStatus": "OFFICIAL",
  "action": {
    "actionType": "OF",
    "serverPlayer": "117365",
    "serverReceiver": "133814",
    "serverNext": "117365",
    "serverCompetitor": "40379",
    "receiverNext": "133814"
  },
  "resultSet": null,
  "matchDateTime": {
    "duration": "00:43:20",
    "startDateLocal": "05/07/2024 11:40:00",
    "startDateUTC": "05/07/2024 08:40:00"
  },
  "teamParentData": null,
  "playByPlaySequenceNumber": "263",
  "teamMatchNo": "0",
  "teamMatchScores": "0-0,0-0,0-0,0-0,0-0",
  "teamMatchScoresSummary": "0"
}