{
  "eventId": "2870",
  "documentCode": "TTEWDOUBLES-----------RND2000400----------",
  "subEventName": "Women's Doubles",
  "subEventDescription": "Women's Doubles - Qualifying Round 2 - Match 4",
  "matchConfig": {
    "bestOfXGames": 5,
    "maxPointsPerGame": 11,
    "advantagePerGame": 2,
    "suddenDeathPoint": 99,
    "maxChallengesPerCompetitor": 99,
    "yellowCard": true,
    "yellowRed1": true,
    "yellowRed2": true,
    "tTRReview": false
  },
  "venueName": "Hala Tivoli",
  "tableNumber": "T04",
  "tableName": "Table 4",
  "competitiors": [
    {
      "competitorType": "H",
      "competitiorId": "38570",
      "competitiorName": "PAULIN Lea/STRAZAR Katarina",
      "competitiorOrg": "SLO",
      "compCardY": "0",
      "compCardYR1": "0",
      "compCardYR2": "0",
      "compTimeout": "1",
      "compMedicalTimeout": "",
      "players": [
        {
          "playerId": "123667",
          "playerName": "PAULIN Lea",
          "playerGivenName": null,
          "playerFamilyName": null,
          "playerOrgCode": "SLO",
          "playerPosition": 1
        },
        {
          "playerId": "123666",
          "playerName": "STRAZAR Katarina",
          "playerGivenName": null,
          "playerFamilyName": null,
          "playerOrgCode": "SLO",
          "playerPosition": 2
        }
      ],
      "scores": "11,9,11,14,0",
      "irm": null
    },
    {
      "competitorType": "A",
      "competitiorId": "38790",
      "competitiorName": "BERGAND Filippa/KALLBERG Christina",
      "competitiorOrg": "SWE",
      "compCardY": "0",
      "compCardYR1": "0",
      "compCardYR2": "0",
      "compTimeout": "1",
      "compMedicalTimeout": "",
      "players": [
        {
          "playerId": "120125",
          "playerName": "BERGAND Filippa",
          "playerGivenName": null,
          "playerFamilyName": null,
          "playerOrgCode": "SWE",
          "playerPosition": 1
        },
        {
          "playerId": "118507",
          "playerName": "KALLBERG Christina",
          "playerGivenName": null,
          "playerFamilyName": null,
          "playerOrgCode": "SWE",
          "playerPosition": 2
        }
      ],
      "scores": "5,11,6,12,0",
      "irm": null
    }
  ],
  "currentGameNumber": 4,
  "full_msg": null,
  "gameScores": "11-5,9-11,11-6,14-12,0-0",
  "resultsGameScores": "11-5,9-11,11-6,14-12,0-0",
  "overallScores": "3-1",
  "resultOverallScores": "3-1",
  "resultStatus": "OFFICIAL",
  "action": {
    "actionType": "OF",
    "serverPlayer": "118507",
    "serverReceiver": "123667",
    "serverNext": "118507",
    "serverCompetitor": "38790",
    "receiverNext": "123667"
  },
  "resultSet": null,
  "matchDateTime": {
    "duration": "00:34:22",
    "startDateLocal": "06/12/2024 14:15:00",
    "startDateUTC": "06/12/2024 12:15:00"
  },
  "teamParentData": null,
  "playByPlaySequenceNumber": "233",
  "teamMatchNo": "0",
  "teamMatchScores": "0-0,0-0,0-0,0-0,0-0",
  "teamMatchScoresSummary": "0"
}