{
  "eventId": "2611",
  "documentCode": "TTEXDOUBLES-----------R32-001400----------",
  "subEventName": "Mixed Doubles",
  "subEventDescription": "Mixed Doubles - Round of 32 - Match 14",
  "matchConfig": {
    "bestOfXGames": 5,
    "maxPointsPerGame": 11,
    "advantagePerGame": 2,
    "suddenDeathPoint": 99,
    "maxChallengesPerCompetitor": 2,
    "yellowCard": true,
    "yellowRed1": true,
    "yellowRed2": true,
    "tTRReview": false
  },
  "venueName": " Centro de Entrenamiento Olimpico",
  "tableNumber": "T02",
  "tableName": "Table 2",
  "competitiors": [
    {
      "competitorType": "H",
      "competitiorId": "134097_100642",
      "competitiorName": "ARAYA Daniel/ARAYA Angie",
      "competitiorOrg": "CRC",
      "compCardY": "0",
      "compCardYR1": "0",
      "compCardYR2": "0",
      "compTimeout": "0",
      "compMedicalTimeout": "",
      "players": [
        {
          "playerId": "134097",
          "playerName": "ARAYA Daniel",
          "playerGivenName": null,
          "playerFamilyName": null,
          "playerOrgCode": null,
          "playerPosition": 1
        },
        {
          "playerId": "100642",
          "playerName": "ARAYA Angie",
          "playerGivenName": null,
          "playerFamilyName": null,
          "playerOrgCode": null,
          "playerPosition": 2
        }
      ],
      "scores": "11,11,11,0,0",
      "irm": null
    },
    {
      "competitorType": "A",
      "competitiorId": "121278_131618",
      "competitiorName": "ARCE Dario/BARCENAS Clio",
      "competitiorOrg": "MEX",
      "compCardY": "0",
      "compCardYR1": "0",
      "compCardYR2": "0",
      "compTimeout": "0",
      "compMedicalTimeout": "",
      "players": [
        {
          "playerId": "121278",
          "playerName": "ARCE Dario",
          "playerGivenName": null,
          "playerFamilyName": null,
          "playerOrgCode": null,
          "playerPosition": 1
        },
        {
          "playerId": "131618",
          "playerName": "BARCENAS Clio",
          "playerGivenName": null,
          "playerFamilyName": null,
          "playerOrgCode": null,
          "playerPosition": 2
        }
      ],
      "scores": "0,0,0,0,0",
      "irm": null
    }
  ],
  "currentGameNumber": 3,
  "full_msg": null,
  "gameScores": "11-0,11-0,11-0,0-0,0-0",
  "resultsGameScores": "11-0,11-0,11-0,0-0,0-0",
  "overallScores": "3-0 WO",
  "resultOverallScores": "3-0",
  "resultStatus": "OFFICIAL",
  "action": {
    "actionType": "OF",
    "serverPlayer": "",
    "serverReceiver": "",
    "serverNext": "",
    "serverCompetitor": "",
    "receiverNext": ""
  },
  "resultSet": null,
  "matchDateTime": {
    "duration": "00:00:00",
    "startDateLocal": "11/02/2022 10:30:00",
    "startDateUTC": "11/02/2022 13:30:00"
  },
  "teamParentData": null,
  "playByPlaySequenceNumber": "2"
}