{
  "eventId": "3128",
  "documentCode": "TTEWDOUBLES-----------8FNL000300----------",
  "subEventName": "Women's Doubles",
  "subEventDescription": "Women's Doubles R 16 - Match 3",
  "matchConfig": {
    "bestOfXGames": 5,
    "maxPointsPerGame": 11,
    "advantagePerGame": 2,
    "suddenDeathPoint": 99,
    "maxChallengesPerCompetitor": 2,
    "yellowCard": true,
    "yellowRed1": true,
    "yellowRed2": true,
    "tTRReview": true
  },
  "venueName": "Baltiska Hallen",
  "tableNumber": "T03",
  "tableName": "Table 3",
  "competitiors": [
    {
      "competitorType": "H",
      "competitiorId": "46604",
      "competitiorName": "KIM Nayeong/RYU Hanna",
      "competitiorOrg": "KOR",
      "compCardY": "0",
      "compCardYR1": "0",
      "compCardYR2": "0",
      "compTimeout": "1",
      "compMedicalTimeout": "",
      "players": [
        {
          "playerId": "133814",
          "playerName": "KIM Nayeong",
          "playerGivenName": null,
          "playerFamilyName": null,
          "playerOrgCode": "KOR",
          "playerPosition": 1
        },
        {
          "playerId": "132701",
          "playerName": "RYU Hanna",
          "playerGivenName": null,
          "playerFamilyName": null,
          "playerOrgCode": "KOR",
          "playerPosition": 2
        }
      ],
      "scores": "9,12,7,11,11",
      "irm": null
    },
    {
      "competitorType": "A",
      "competitiorId": "36036",
      "competitiorName": "PARANANG Orawan/SAWETTABUT Suthasini",
      "competitiorOrg": "THA",
      "compCardY": "0",
      "compCardYR1": "0",
      "compCardYR2": "0",
      "compTimeout": "1",
      "compMedicalTimeout": "",
      "players": [
        {
          "playerId": "120972",
          "playerName": "PARANANG Orawan",
          "playerGivenName": null,
          "playerFamilyName": null,
          "playerOrgCode": "THA",
          "playerPosition": 1
        },
        {
          "playerId": "111833",
          "playerName": "SAWETTABUT Suthasini",
          "playerGivenName": null,
          "playerFamilyName": null,
          "playerOrgCode": "THA",
          "playerPosition": 2
        }
      ],
      "scores": "11,10,11,7,8",
      "irm": null
    }
  ],
  "currentGameNumber": 5,
  "full_msg": null,
  "gameScores": "9-11,12-10,7-11,11-7,11-8",
  "resultsGameScores": "9-11,12-10,7-11,11-7,11-8",
  "overallScores": "3-2",
  "resultOverallScores": "3-2",
  "resultStatus": "OFFICIAL",
  "action": {
    "actionType": "OF",
    "serverPlayer": "133814",
    "serverReceiver": "111833",
    "serverNext": "133814",
    "serverCompetitor": "46604",
    "receiverNext": "111833"
  },
  "resultSet": null,
  "matchDateTime": {
    "duration": "00:38:43",
    "startDateLocal": "08/20/2025 19:45:00",
    "startDateUTC": "08/20/2025 17:45:00"
  },
  "teamParentData": null,
  "playByPlaySequenceNumber": "280",
  "teamMatchNo": "0",
  "teamMatchScores": "0-0,0-0,0-0,0-0,0-0",
  "teamMatchScoresSummary": "0",
  "matchStartTimeUTC": "2025-08-20T18:26:43.31Z"
}