{
  "eventId": "2522",
  "documentCode": "TTEWDOUBLES-----------QFNL000100----------",
  "subEventName": "Women's Doubles",
  "subEventDescription": "Women's Doubles - Quarterfinals - Match 1",
  "matchConfig": {
    "bestOfXGames": 5,
    "maxPointsPerGame": 11,
    "advantagePerGame": 2,
    "suddenDeathPoint": 99,
    "maxChallengesPerCompetitor": 99,
    "yellowCard": true,
    "yellowRed1": true,
    "yellowRed2": true,
    "tTRReview": false
  },
  "venueName": "Deutsches Tischtennis- Zentrum",
  "tableNumber": "T04",
  "tableName": "Table 4",
  "competitiors": [
    {
      "competitorType": "H",
      "competitiorId": "43748",
      "competitiorName": "LUTZ Charlotte/COK Isa",
      "competitiorOrg": "FRA",
      "compCardY": "0",
      "compCardYR1": "0",
      "compCardYR2": "0",
      "compTimeout": "0",
      "compMedicalTimeout": "",
      "players": [
        {
          "playerId": "135501",
          "playerName": "LUTZ Charlotte",
          "playerGivenName": null,
          "playerFamilyName": null,
          "playerOrgCode": null,
          "playerPosition": 1
        },
        {
          "playerId": "131846",
          "playerName": "COK Isa",
          "playerGivenName": null,
          "playerFamilyName": null,
          "playerOrgCode": null,
          "playerPosition": 2
        }
      ],
      "scores": "11,11,11,0,0",
      "irm": null
    },
    {
      "competitorType": "A",
      "competitiorId": "40215",
      "competitiorName": "MOSTAFAVI Leili/GUISNEL Oceane",
      "competitiorOrg": "FRA",
      "compCardY": "0",
      "compCardYR1": "0",
      "compCardYR2": "0",
      "compTimeout": "1",
      "compMedicalTimeout": "",
      "players": [
        {
          "playerId": "120112",
          "playerName": "MOSTAFAVI Leili",
          "playerGivenName": null,
          "playerFamilyName": null,
          "playerOrgCode": null,
          "playerPosition": 1
        },
        {
          "playerId": "121688",
          "playerName": "GUISNEL Oceane",
          "playerGivenName": null,
          "playerFamilyName": null,
          "playerOrgCode": null,
          "playerPosition": 2
        }
      ],
      "scores": "4,6,9,0,0",
      "irm": null
    }
  ],
  "currentGameNumber": 3,
  "full_msg": null,
  "gameScores": "11-4,11-6,11-9,0-0,0-0",
  "resultsGameScores": "11-4,11-6,11-9,0-0,0-0",
  "overallScores": "3-0",
  "resultOverallScores": "3-0",
  "resultStatus": "OFFICIAL",
  "action": {
    "actionType": "OF",
    "serverPlayer": "",
    "serverReceiver": "",
    "serverNext": "",
    "serverCompetitor": "",
    "receiverNext": ""
  },
  "resultSet": null,
  "matchDateTime": {
    "duration": "00:21:27",
    "startDateLocal": "01/19/2022 10:49:34",
    "startDateUTC": "01/19/2022 09:49:34"
  },
  "teamParentData": null,
  "playByPlaySequenceNumber": "156"
}