{
  "eventId": "2511",
  "documentCode": "TTEMSINGLES--------U19QFNL000100----------",
  "subEventName": "U19 Boys' Singles",
  "subEventDescription": "U19 Boys' Singles - Quarterfinals - Match 1",
  "matchConfig": {
    "bestOfXGames": 7,
    "maxPointsPerGame": 11,
    "advantagePerGame": 2,
    "suddenDeathPoint": 99,
    "maxChallengesPerCompetitor": 2,
    "yellowCard": true,
    "yellowRed1": true,
    "yellowRed2": true,
    "tTRReview": false
  },
  "venueName": "Pavilhão Desportivo Municipal de Gaia",
  "tableNumber": "T01",
  "tableName": "Table 1",
  "competitiors": [
    {
      "competitorType": "H",
      "competitiorId": "135888",
      "competitiorName": "XIANG Peng",
      "competitiorOrg": "CHN",
      "compCardY": "0",
      "compCardYR1": "0",
      "compCardYR2": "0",
      "compTimeout": "0",
      "compMedicalTimeout": "",
      "players": [
        {
          "playerId": "135888",
          "playerName": "XIANG Peng",
          "playerGivenName": null,
          "playerFamilyName": null,
          "playerOrgCode": null,
          "playerPosition": 1
        }
      ],
      "scores": "11,9,11,11,11,0,0",
      "irm": null
    },
    {
      "competitorType": "A",
      "competitiorId": "124576",
      "competitiorName": "SIDORENKO Vladimir",
      "competitiorOrg": "RUS",
      "compCardY": "0",
      "compCardYR1": "0",
      "compCardYR2": "0",
      "compTimeout": "0",
      "compMedicalTimeout": "",
      "players": [
        {
          "playerId": "124576",
          "playerName": "SIDORENKO Vladimir",
          "playerGivenName": null,
          "playerFamilyName": null,
          "playerOrgCode": null,
          "playerPosition": 2
        }
      ],
      "scores": "9,11,4,7,7,0,0",
      "irm": null
    }
  ],
  "currentGameNumber": 5,
  "full_msg": null,
  "gameScores": "11-9,9-11,11-4,11-7,11-7,0-0,0-0",
  "resultsGameScores": "11-9,9-11,11-4,11-7,11-7,0-0,0-0",
  "overallScores": "4-1",
  "resultOverallScores": "4-1",
  "resultStatus": "OFFICIAL",
  "action": {
    "actionType": "OF",
    "serverPlayer": "124576",
    "serverReceiver": "135888",
    "serverNext": "124576",
    "serverCompetitor": "124576",
    "receiverNext": "124576"
  },
  "resultSet": null,
  "matchDateTime": {
    "duration": "00:40:00",
    "startDateLocal": "12/07/2021 11:00:00",
    "startDateUTC": "12/07/2021 11:00:00"
  },
  "teamParentData": null,
  "playByPlaySequenceNumber": "2"
}