{
  "eventId": "2591",
  "documentCode": "TTEXDOUBLES-----------8FNL000800----------",
  "subEventName": "Mixed Doubles",
  "subEventDescription": "Mixed Doubles - Round of 16 - Match 8",
  "matchConfig": {
    "bestOfXGames": 5,
    "maxPointsPerGame": 11,
    "advantagePerGame": 2,
    "suddenDeathPoint": 99,
    "maxChallengesPerCompetitor": 99,
    "yellowCard": true,
    "yellowRed1": true,
    "yellowRed2": true,
    "tTRReview": false
  },
  "venueName": "BOK Hall",
  "tableNumber": "T03",
  "tableName": "Table 3",
  "competitiors": [
    {
      "competitorType": "H",
      "competitiorId": "47629",
      "competitiorName": "UDA Yukiya/ITO Mima",
      "competitiorOrg": "JPN",
      "compCardY": "0",
      "compCardYR1": "0",
      "compCardYR2": "0",
      "compTimeout": "1",
      "compMedicalTimeout": "",
      "players": [
        {
          "playerId": "122777",
          "playerName": "UDA Yukiya",
          "playerGivenName": null,
          "playerFamilyName": null,
          "playerOrgCode": null,
          "playerPosition": 1
        },
        {
          "playerId": "117821",
          "playerName": "ITO Mima",
          "playerGivenName": null,
          "playerFamilyName": null,
          "playerOrgCode": null,
          "playerPosition": 2
        }
      ],
      "scores": "11,11,5,7,7"
    },
    {
      "competitorType": "A",
      "competitiorId": "37084",
      "competitiorName": "HARIMOTO Tomokazu/HAYATA Hina",
      "competitiorOrg": "JPN",
      "compCardY": "0",
      "compCardYR1": "0",
      "compCardYR2": "0",
      "compTimeout": "1",
      "compMedicalTimeout": "",
      "players": [
        {
          "playerId": "123980",
          "playerName": "HARIMOTO Tomokazu",
          "playerGivenName": null,
          "playerFamilyName": null,
          "playerOrgCode": null,
          "playerPosition": 1
        },
        {
          "playerId": "123672",
          "playerName": "HAYATA Hina",
          "playerGivenName": null,
          "playerFamilyName": null,
          "playerOrgCode": null,
          "playerPosition": 2
        }
      ],
      "scores": "6,9,11,11,11"
    }
  ],
  "currentGameNumber": 5,
  "full_msg": null,
  "gameScores": "11-6,11-9,5-11,7-11,7-11",
  "resultsGameScores": "11-6,11-9,5-11,7-11,7-11",
  "overallScores": "2-3",
  "resultOverallScores": "2-3",
  "resultStatus": "OFFICIAL",
  "action": {
    "actionType": "OF",
    "serverPlayer": "",
    "serverReceiver": "",
    "serverNext": "",
    "serverCompetitor": "",
    "receiverNext": ""
  },
  "resultSet": null,
  "matchDateTime": {
    "duration": "00:45:00",
    "startDateLocal": "07/13/2022 09:34:46",
    "startDateUTC": "07/13/2022 07:34:46"
  },
  "teamParentData": null
}