{
  "eventId": "2609",
  "documentCode": "TTEWDOUBLES-----------QFNL000200----------",
  "subEventName": "Women's Doubles",
  "subEventDescription": "Women's Doubles - Quarterfinal - Match 2",
  "matchConfig": {
    "bestOfXGames": 7,
    "maxPointsPerGame": 11,
    "advantagePerGame": 2,
    "suddenDeathPoint": 99,
    "maxChallengesPerCompetitor": 2,
    "yellowCard": true,
    "yellowRed1": true,
    "yellowRed2": true,
    "tTRReview": true
  },
  "venueName": "La Coupole- Cit? Olympique",
  "tableNumber": "T02",
  "tableName": "Table 2",
  "competitiors": [
    {
      "competitorType": "H",
      "competitiorId": "58899",
      "competitiorName": "SIDDEKI Narimene-Hind/ZOGHLAMI Maram",
      "competitiorOrg": "ALG/TUN",
      "compCardY": "0",
      "compCardYR1": "0",
      "compCardYR2": "0",
      "compTimeout": "0",
      "compMedicalTimeout": "",
      "players": [
        {
          "playerId": "134953",
          "playerName": "SIDDEKI Narimene-Hind",
          "playerGivenName": null,
          "playerFamilyName": null,
          "playerOrgCode": null,
          "playerPosition": 1
        },
        {
          "playerId": "131741",
          "playerName": "ZOGHLAMI Maram",
          "playerGivenName": null,
          "playerFamilyName": null,
          "playerOrgCode": null,
          "playerPosition": 2
        }
      ],
      "scores": "11,11,9,14,13,0,0"
    },
    {
      "competitorType": "A",
      "competitiorId": "36399",
      "competitiorName": "HOSENALLY Oumehani/JALIM Nandeshwaree",
      "competitiorOrg": "MRI",
      "compCardY": "0",
      "compCardYR1": "0",
      "compCardYR2": "0",
      "compTimeout": "1",
      "compMedicalTimeout": "",
      "players": [
        {
          "playerId": "136521",
          "playerName": "HOSENALLY Oumehani",
          "playerGivenName": null,
          "playerFamilyName": null,
          "playerOrgCode": null,
          "playerPosition": 1
        },
        {
          "playerId": "131818",
          "playerName": "JALIM Nandeshwaree",
          "playerGivenName": null,
          "playerFamilyName": null,
          "playerOrgCode": null,
          "playerPosition": 2
        }
      ],
      "scores": "8,4,11,12,11,0,0"
    }
  ],
  "currentGameNumber": 5,
  "full_msg": null,
  "gameScores": "11-8,11-4,9-11,14-12,13-11,0-0,0-0",
  "resultsGameScores": "11-8,11-4,9-11,14-12,13-11,0-0,0-0",
  "overallScores": "4-1",
  "resultOverallScores": "4-1",
  "resultStatus": "OFFICIAL",
  "action": {
    "actionType": "OF",
    "serverPlayer": "",
    "serverReceiver": "",
    "serverNext": "",
    "serverCompetitor": "",
    "receiverNext": ""
  },
  "resultSet": null,
  "matchDateTime": {
    "duration": "00:38:17",
    "startDateLocal": "09/08/2022 10:04:05",
    "startDateUTC": "09/08/2022 09:04:05"
  },
  "teamParentData": null
}