{
  "eventId": "2964",
  "documentCode": "TTEXDOUBLES-----------8FNL000400----------",
  "subEventName": "Mixed Doubles",
  "subEventDescription": "Mixed Doubles - Round of 16 - Match 4",
  "matchConfig": {
    "bestOfXGames": 5,
    "maxPointsPerGame": 11,
    "advantagePerGame": 2,
    "suddenDeathPoint": 99,
    "maxChallengesPerCompetitor": 99,
    "yellowCard": true,
    "yellowRed1": true,
    "yellowRed2": true,
    "tTRReview": false
  },
  "venueName": "Sport Hall 1 Tetori ",
  "tableNumber": "T01",
  "tableName": "Table 1",
  "competitiors": [
    {
      "competitorType": "H",
      "competitiorId": "100122006",
      "competitiorName": "HAN Eunho/LEE Daeun",
      "competitiorOrg": "KOR",
      "compCardY": "0",
      "compCardYR1": "0",
      "compCardYR2": "0",
      "compTimeout": "1",
      "compMedicalTimeout": "",
      "players": [
        {
          "playerId": "208509",
          "playerName": "HAN Eunho",
          "playerGivenName": null,
          "playerFamilyName": null,
          "playerOrgCode": "KOR",
          "playerPosition": 1
        },
        {
          "playerId": "135391",
          "playerName": "LEE Daeun",
          "playerGivenName": null,
          "playerFamilyName": null,
          "playerOrgCode": "KOR",
          "playerPosition": 2
        }
      ],
      "scores": "11,6,11,7,11",
      "irm": null
    },
    {
      "competitorType": "A",
      "competitiorId": "100122005",
      "competitiorName": "BAEK Hogyun/CHOI Hyojoo",
      "competitiorOrg": "KOR",
      "compCardY": "0",
      "compCardYR1": "0",
      "compCardYR2": "0",
      "compTimeout": "0",
      "compMedicalTimeout": "",
      "players": [
        {
          "playerId": "133717",
          "playerName": "BAEK Hogyun",
          "playerGivenName": null,
          "playerFamilyName": null,
          "playerOrgCode": "KOR",
          "playerPosition": 1
        },
        {
          "playerId": "131401",
          "playerName": "CHOI Hyojoo",
          "playerGivenName": null,
          "playerFamilyName": null,
          "playerOrgCode": "KOR",
          "playerPosition": 2
        }
      ],
      "scores": "6,11,8,11,13",
      "irm": null
    }
  ],
  "currentGameNumber": 5,
  "full_msg": null,
  "gameScores": "11-6,6-11,11-8,7-11,11-13",
  "resultsGameScores": "11-6,6-11,11-8,7-11,11-13",
  "overallScores": "2-3",
  "resultOverallScores": "2-3",
  "resultStatus": "OFFICIAL",
  "action": {
    "actionType": "OF",
    "serverPlayer": "208509",
    "serverReceiver": "131401",
    "serverNext": "208509",
    "serverCompetitor": "100122006",
    "receiverNext": "131401"
  },
  "resultSet": null,
  "matchDateTime": {
    "duration": "00:44:23",
    "startDateLocal": "10/30/2024 10:35:00",
    "startDateUTC": "10/30/2024 09:35:00"
  },
  "teamParentData": null,
  "playByPlaySequenceNumber": "268",
  "teamMatchNo": "0",
  "teamMatchScores": "0-0,0-0,0-0,0-0,0-0",
  "teamMatchScoresSummary": "0"
}